pytorchlight/__init__.py
pytorchlight/adversarial/__init__.py
pytorchlight/adversarial/fgsm.py
pytorchlight/utils/__init__.py
pytorchlight/utils/data.py
pytorchlight/utils/log.py
pytorchlight/utils/model.py
pytorchlight/utils/visual.py
pytorchlight-0.0.1.dist-info/LICENSE
pytorchlight-0.0.1.dist-info/METADATA
pytorchlight-0.0.1.dist-info/WHEEL
pytorchlight-0.0.1.dist-info/top_level.txt
pytorchlight-0.0.1.dist-info/RECORD
