Metadata-Version: 2.1
Name: pytorchlight
Version: 0.0.1
Summary: Easy-to-run Application based on PyTorch
Home-page: https://github.com/mechanicalsea/pytorch-light
Author: Rui Wang
Author-email: wangrui_key@163.com
License: BSD
Platform: UNKNOWN
Classifier: Programming Language :: Python :: 3.5
Classifier: License :: OSI Approved :: BSD License
Classifier: Operating System :: Microsoft :: Windows :: Windows 10
Requires-Dist: logging (==0.5.1.2)
Requires-Dist: numpy (==1.15.2)
Requires-Dist: matplotlib (==2.1.1)
Requires-Dist: torch (==1.0.1)
Requires-Dist: torchvision (==0.2.2)
